otsutil/__init__.py
otsutil/classes.py
otsutil/funcs.py
otsutil-2022.11.25.dist-info/LICENSE.txt
otsutil-2022.11.25.dist-info/METADATA
otsutil-2022.11.25.dist-info/WHEEL
otsutil-2022.11.25.dist-info/top_level.txt
otsutil-2022.11.25.dist-info/RECORD
