Metadata-Version: 2.1
Name: otsutil
Version: 2022.11.25
Summary: よく使う関数、クラスを纏めたライブラリ
Home-page: https://github.com/Otsuhachi/Otsutil
Author: Otsuhachi
Author-email: agequodagis.tufuiegoeris@gmail.com
Keywords: Python ObjectSaver deduplicate load_json read_lines save_json setup_path write_lines timer
Classifier: Development Status :: 1 - Planning
Classifier: Natural Language :: Japanese
Classifier: Programming Language :: Python :: 3
Classifier: Programming Language :: Python :: 3.5
Classifier: Programming Language :: Python :: 3.6
Classifier: Programming Language :: Python :: 3.7
Classifier: Programming Language :: Python :: 3.8
Classifier: Programming Language :: Python :: 3.9
Classifier: Programming Language :: Python :: 3.10
Classifier: Operating System :: Microsoft :: Windows :: Windows 10
Classifier: License :: OSI Approved :: MIT License
License-File: LICENSE.txt
